<?xml version="1.0" encoding="utf-8" ?>
<dwsync>
<file name="SuppList.asp" local="129433741657077174" remote="129433740020000000" testing="129433740020000000" />
<file name="First.gif" local="129392394443324658" remote="129392392370000000" testing="129392392370000000" />
<file name="Last.gif" local="129392394443637154" remote="129392392370000000" testing="129392392370000000" />
<file name="Next.gif" local="129392394443480906" remote="129392392370000000" testing="129392392370000000" />
<file name="Previous.gif" local="129392394443480906" remote="129392392370000000" testing="129392392370000000" />
<file name="css.css" local="129482069780000000" remote="131317975200000000" testing="129416530080000000" />
<file name="parent.asp" local="129435271334282940" remote="129435269030000000" testing="129435269030000000" />
<file name="dcollate.asp" local="129452900643605627" remote="129452899870000000" testing="129452899870000000" />
<file name="pdetail.asp" local="129434723476329258" remote="129434719270000000" testing="129434719270000000" />
<file name="tj.jsp" local="129434778526583782" remote="129434775100000000" testing="129434775100000000" />
<file name="tj2.jsp" local="129434780909392183" remote="129434779400000000" testing="129434779400000000" />
<file name="collate.asp" local="129457001155073639" remote="129456997270000000" testing="129456997270000000" />
<file name="default.asp" local="129451785991794671" remote="129451783180000000" testing="129451783180000000" />
<file name="Ordersx.asp" local="131317972212307427" remote="131317973400000000" testing="0" />
</dwsync>